{"id": "collections", "path": "/home/jhc/.local/lib/mypy/typeshed/stdlib/3/collections/__init__.pyi", "mtime": 1515851272, "size": 13640, "hash": "b1e84d51473e2fca8f13fda309f890e8", "data_mtime": 1529220729, "dependencies": ["sys", "typing", "collections.abc", "builtins"], "suppressed": [], "child_modules": ["collections.abc"], "options": {"platform": "linux", "ignore_errors": false, "warn_no_return": true, "disallow_untyped_calls": false, "ignore_missing_imports": false, "disallow_subclassing_any": false, "disallow_untyped_defs": false, "quick_and_dirty": false, "disallow_any_expr": false, "strict_optional": false, "no_implicit_optional": false, "show_none_errors": true, "disallow_any_decorated": false, "strict_optional_whitelist": null, "warn_return_any": false, "disallow_any_unimported": false, "disallow_untyped_decorators": false, "strict_boolean": false, "follow_imports": "normal", "check_untyped_defs": false, "disallow_any_explicit": false, "disallow_any_generics": false}, "dep_prios": [10, 5, 10, 5], "interface_hash": "e5449c8644ee7694722a5e4ac4b722a6", "version_id": "0.560", "ignore_all": false}
